Workbook

Sheet Параметры
A1: Параметры оценки выбросов АО «Невинномысский Азот»
A2: Синий шрифт — вводимые значения; жёлтая заливка — параметры, которые нужно запросить у предприятия. Класс: A — первичный документ о «Азоте», B — расчёт по аналогам, C — вторичный источник или допущение.
A4: Код | B4: Параметр | C4: Ед. | D4: Значение | E4: Мин. | F4: Макс. | G4: Класс | H4: Источник / основание
A5: CAP | B5: Мощность «Азота» по аммиаку | C5: кт/год | D5: 1160 | E5: 1000 | F5: 1350 | G5: C | H5: Открытые материалы, диапазон 1,0–1,35 млн т; принято как в § 3.1. СМИ (2025): «до 1 млн т аммиака». Сверить с годовым отчётом эмитента
A6: E_TOT | B6: Полные выбросы CO2 на т валовой мощности (медиана 5 заводов CF, 2022–2023) | C6: т/т | D6: =MEDIAN(Аналоги_CF!$F$5:$F$9) -> 1.8793946 | E6: =MIN(Аналоги_CF!$F$5:$F$9) -> 1.7905098 | F6: =MAX(Аналоги_CF!$F$5:$F$9) -> 2.0987901 | G6: B | H6: Лист «Аналоги_CF»: EPA GHGRP / CF Industries 10-K FY2022
A7: E_PROC | B7: Процессный CO2 аммиака на т валовой мощности (медиана CF) | C7: т/т | D7: =MEDIAN(Аналоги_CF!$G$5:$G$9) -> 1.1253674 | E7: =MIN(Аналоги_CF!$G$5:$G$9) -> 1.0117318 | F7: =MAX(Аналоги_CF!$G$5:$G$9) -> 1.3212797 | G7: B | H7: Там же; включает CO2, связываемый затем в карбамид (EPA Subpart G Information Sheet)
A8: AN | B8: Выпуск аммиачной селитры (вкл. на КАС) | C8: кт/год | D8: 1200 | E8: 1000 | F8: 1400 | G8: C | H8: СМИ 2025: «более 1 млн т» и «около 1,4 млн т»; запросить у предприятия
A9: K_HNO3 | B9: Азотная кислота на т селитры (стехиометрия NH4NO3) | C9: т/т | D9: 0.7875 | G9: — | H9: 63/80
A10: EF_N2O | B10: Удельный выброс N2O на т HNO3, Россия, без очистки | C10: кг/т | D10: 8.5 | E10: 8 | F10: 9 | G10: B | H10: Jörß, Ludig, Schneider (Öko-Institut), 2023: Россия 8–9 кг N2O/т HNO3
A11: R_A | B11: Отношение N2O (CO2-экв.) к процессному CO2 у аналогов США, медиана | C11: — | D11: =MEDIAN(Панель_EPA!$L$4:$L$40) -> 0.37298658 | E11: =QUARTILE(Панель_EPA!$L$4:$L$40,1) -> 0.17839597 | F11: =QUARTILE(Панель_EPA!$L$4:$L$40,3) -> 0.70259342 | G11: B | H11: Лист «Аналоги_CF» → «Панель_EPA», 2023; квартили в кол. Мин./Макс.
A12: GWP | B12: Потенциал глобального потепления N2O (AR4) | C12: — | D12: 298 | G12: — | H12: МГЭИК, 4-й оценочный доклад; используется в EPA GHGRP
A13: UREA | B13: Выпуск карбамида | C13: кт/год | D13: 500 | E13: 300 | F13: 700 | G13: C | H13: Сценарное допущение; открытых данных нет. Запросить у предприятия
A14: K_UREA | B14: CO2, связываемый на т карбамида | C14: т/т | D14: 0.733 | G14: — | H14: Стехиометрия CO(NH2)2: 44/60
A15: FOOD | B15: Мощность установки пищевой жидкой углекислоты (с декабря 2018 г.) | C15: кт/год | D15: 32 | G15: C | H15: ЕвроХим, 2018 (см. § 3.1); фактические продажи запросить
A16: D2025 | B16: Дни простоя в 2025 г. (остановка 14.06.2025) | C16: дней | D16: 0 | E16: 0 | F16: 60 | G16: C | H16: Факт остановки — СМИ; длительность не раскрыта. Сценарный рычаг
A17: D2026 | B17: Дни простоя в 2026 г. | C17: дней | D17: 0 | E17: 0 | F17: 60 | G17: C | H17: Удар 16.05.2026 по СМИ, данных о простое нет. 2026 г. — оценка на полный год

Sheet Аналоги_CF
A1: Заводы CF Industries в США: мощность и выбросы
A2: Мощность — CF Industries, Form 10-K FY2022 (валовая, с учётом нормальных простоев); выбросы — EPA GHGRP (Envirofacts), т.
A4: Завод | B4: ID EPA | C4: Мощность NH3, кт | D4: CO2 полный 2023, т | E4: CO2 процесс 2023, т | F4: CO2 полный / мощн., т/т (ср. 2022–23) | G4: CO2 процесс / мощн., т/т (ср. 2022–23) | H4: Индекс масштаба «Азот» / завод | I4: CO2 полный 2022, т | J4: CO2 процесс 2022, т
A5: Donaldsonville | B5: 1002301 | C5: 4335 | D5: 7752761.9 | E5: 4862676.5 | F5: =AVERAGE(D5,I5)/1000/C5 -> 1.7970201 | G5: =AVERAGE(E5,J5)/1000/C5 -> 1.1253674 | H5: =Параметры!$D$5/C5 -> 0.26758939 | I5: 7827402 | J5: 4894258.6
A6: Port Neal | B6: 1006005 | C6: 1230 | D6: 2599267.7 | E6: 1624172.7 | F6: =AVERAGE(D6,I6)/1000/C6 -> 2.0987901 | G6: =AVERAGE(E6,J6)/1000/C6 -> 1.3212797 | H6: =Параметры!$D$5/C6 -> 0.94308943 | I6: 2563756 | J6: 1626175.4
A7: Verdigris | B7: 1002275 | C7: 1210 | D7: 2106706.9 | E7: 1176114 | F7: =AVERAGE(D7,I7)/1000/C7 -> 1.7905098 | G7: =AVERAGE(E7,J7)/1000/C7 -> 1.0117318 | H7: =Параметры!$D$5/C7 -> 0.95867769 | I7: 2226326.9 | J7: 1272276.9
A8: Woodward | B8: 1005788 | C8: 480 | D8: 861840.5 | E8: 509521.6 | F8: =AVERAGE(D8,I8)/1000/C8 -> 1.8793946 | G8: =AVERAGE(E8,J8)/1000/C8 -> 1.1050817 | H8: =Параметры!$D$5/C8 -> 2.4166667 | I8: 942378.3 | J8: 551356.8
A9: Yazoo City | B9: 1004183 | C9: 570 | D9: 1135406.3 | E9: 708631.5 | F9: =AVERAGE(D9,I9)/1000/C9 -> 1.988119 | G9: =AVERAGE(E9,J9)/1000/C9 -> 1.1972761 | H9: =Параметры!$D$5/C9 -> 2.0350877 | I9: 1131049.4 | J9: 656263.3
A11: Индекс масштаба отвечает на вопрос «на сколько “Азот” больше или меньше завода-аналога». По масштабу ближе всего Port Neal и Verdigris (индекс ≈ 0,94–0,96).
A12: Технологический индекс: аналоги США и «Азот» работают на природном газе (паровая конверсия). Угольные заводы Китая примерно вдвое более углеродоёмки (IEA Ammonia Technology Roadmap, 2021), поэтому как аналог по CO2 не используются.

Sheet Панель_EPA
A1: Панель интегрированных азотных комплексов США (EPA GHGRP): процессный CO2 аммиака (Subpart G), т
A2: Отбор: полный ряд 2017–2023, ≥150 кт в 2023, есть отчётность по азотной кислоте, без пусковых лет. Источник: data.epa.gov/efservice, таблицы G_SUBPART_LEVEL_INFORMATION и V_SUBPART_LEVEL_INFORMATION (выгружено 14.10.2026).
A3: Завод | B3: ID | C3: 2017 | D3: 2018 | E3: 2019 | F3: 2020 | G3: 2021 | H3: 2022 | I3: 2023 | J3: N2O 2023, т N2O | K3: N2O/процесс CO2 (CO2-экв.)
A4: Coffeyville (CVR) | B4: 1002170 | C4: 1289892.7 | D4: 1209792.5 | E4: 1426458.4 | F4: 1402799.5 | G4: 1378252.3 | H4: 1126826.9 | I4: 1352802.2 | J4: 803.753 | L4: =IF(J4>1,J4*Параметры!$D$12/I4,"") -> 0.17705352
A5: Lima (Nutrien) | B5: 1002229 | C5: 766476.3 | D5: 803444.1 | E5: 817001.4 | F5: 741786.6 | G5: 931331.6 | H5: 897363.9 | I5: 872546.4 | J5: 0.501 | L5: =IF(J5>1,J5*Параметры!$D$12/I5,"")
A6: Verdigris (CF) | B6: 1002275 | C6: 1314048.5 | D6: 1259232.1 | E6: 1185805.7 | F6: 1306784.9 | G6: 1146954 | H6: 1272276.9 | I6: 1176114 | J6: 4184.545 | L6: =IF(J6>1,J6*Параметры!$D$12/I6,"") -> 1.0602666
A7: Donaldsonville (CF) | B7: 1002301 | C7: 4850956.3 | D7: 4645994.5 | E7: 5000921.4 | F7: 4724629.3 | G7: 4461915.9 | H7: 4894258.6 | I7: 4862676.5 | J7: 5770.118 | L7: =IF(J7>1,J7*Параметры!$D$12/I7,"") -> 0.35361085
A8: Enid (Koch) | B8: 1002407 | C8: 954782.1 | D8: 1041223.7 | E8: 1285652.8 | F8: 1381943.4 | G8: 1208341.7 | H8: 1293541.3 | I8: 1348509.2 | J8: 0.483 | L8: =IF(J8>1,J8*Параметры!$D$12/I8,"")
A9: Geismar (Nutrien) | B9: 1003489 | C9: 524760.6 | D9: 486970.5 | E9: 602461.6 | F9: 594200.4 | G9: 579506.5 | H9: 655178 | I9: 515726.2 | J9: 2642.044 | L9: =IF(J9>1,J9*Параметры!$D$12/I9,"") -> 1.5266417
A10: El Dorado (LSB) | B10: 1003993 | C10: 458816.2 | D10: 501287.8 | E10: 466390.3 | F10: 497381.5 | G10: 487218.3 | H10: 483118.7 | I10: 521423.3 | J10: 312.93 | L10: =IF(J10>1,J10*Параметры!$D$12/I10,"") -> 0.17884345
A11: Yazoo City (CF) | B11: 1004183 | C11: 638808.2 | D11: 637681.1 | E11: 623918.4 | F11: 674644.2 | G11: 541249.5 | H11: 656263.3 | I11: 708631.5 | J11: 4355.939 | L11: =IF(J11>1,J11*Параметры!$D$12/I11,"") -> 1.8317981
A12: Augusta (Nutrien) | B12: 1004340 | C12: 873380.1 | D12: 1042653.4 | E12: 1015785 | F12: 970581.7 | G12: 1033658 | H12: 902857.3 | I12: 1126460.7 | J12: 195.488 | L12: =IF(J12>1,J12*Параметры!$D$12/I12,"") -> 0.051715452
A13: East Dubuque (CVR) | B13: 1005502 | C13: 399923.9 | D13: 414103.8 | E13: 357115 | F13: 455518.9 | G13: 436217 | H13: 368048 | I13: 457458.9 | J13: 234.34 | L13: =IF(J13>1,J13*Параметры!$D$12/I13,"") -> 0.15265485
A14: Woodward (CF) | B14: 1005788 | C14: 476676.4 | D14: 532282.9 | E14: 475800.5 | F14: 584415.7 | G14: 522816.4 | H14: 551356.8 | I14: 509521.6 | J14: 1101.662 | L14: =IF(J14>1,J14*Параметры!$D$12/I14,"") -> 0.64432063
A15: Pryor (LSB) | B15: 1005867 | C15: 179345.1 | D15: 220014.9 | E15: 187119.9 | F15: 232171.7 | G15: 200914.5 | H15: 201649 | I15: 240926.1 | J15: 264.55 | L15: =IF(J15>1,J15*Параметры!$D$12/I15,"") -> 0.32722026
... A21: Cherokee (LSB) | B21: 1007770 | C21: 201375.6 | D21: 162701.6 | E21: 192606 | F21: 205894.3 | G21: 179240.1 | H21: 182345.6 | I21: 193859.4 | J21: 570.787 | L21: =IF(J21>1,J21*Параметры!$D$12/I21,"") -> 0.8774118
A23: Индекс выбросов к 2017 г.: медиана по заводам
A24: медиана I(t) | C24: =MEDIAN(C4/C4,C5/C5,C6/C6,C7/C7,C8/C8,C9/C9,C10/C10,C11/C11,C12/C12,C13/C13,C14/C14,C15/C15,C16/C16,C17/C17,C18/C18,C19/C19,C20/C20,C21/C21) -> 1 | D24: =MEDIAN(D4/C4,D5/C5,D6/C6,D7/C7,D8/C8,D9/C9,D10/C10,D11/C11,D12/C12,D13/C13,D14/C14,D15/C15,D16/C16,D17/C17,D18/C18,D19/C19,D20/C20,D21/C21) -> 1.0418437 | E24: =MEDIAN(E4/C4,E5/C5,E6/C6,E7/C7,E8/C8,E9/C9,E10/C10,E11/C11,E12/C12,E13/C13,E14/C14,E15/C15,E16/C16,E17/C17,E18/C18,E19/C19,E20/C20,E21/C21) -> 1.0281968 | F24: =MEDIAN(F4/C4,F5/C5,F6/C6,F7/C7,F8/C8,F9/C9,F10/C10,F11/C11,F12/C12,F13/C13,F14/C14,F15/C15,F16/C16,F17/C17,F18/C18,F19/C19,F20/C20,F21/C21) -> 1.0857929 | G24: =MEDIAN(G4/C4,G5/C5,G6/C6,G7/C7,G8/C8,G9/C9,G10/C10,G11/C11,G12/C12,G13/C13,G14/C14,G15/C15,G16/C16,G17/C17,G18/C18,G19/C19,G20/C20,G21/C21) -> 1.0652023 | H24: =MEDIAN(H4/C4,H5/C5,H6/C6,H7/C7,H8/C8,H9/C9,H10/C10,H11/C11,H12/C12,H13/C13,H14/C14,H15/C15,H16/C16,H17/C17,H18/C18,H19/C19,H20/C20,H21/C21) -> 1.054172 | I24: =MEDIAN(I4/C4,I5/C5,I6/C6,I7/C7,I8/C8,I9/C9,I10/C10,I11/C11,I12/C12,I13/C13,I14/C14,I15/C15,I16/C16,I17/C17,I18/C18,I19/C19,I20/C20,I21/C21) -> 1.0722465
A25: Годовой эффект exp(γt), модель с фиксированными эффектами (лог.) | C25: 1 | D25: 1.0333593 | E25: 1.0350458 | F25: 1.1005603 | G25: 1.0337595 | H25: 1.0520477 | I25: 1.0845127
A26: 95 % интервал, нижняя граница (бутстреп 2000) | C26: 1 | D26: 0.98774568 | E26: 0.98946593 | F26: 1.0560241 | G26: 0.97694314 | H26: 0.99732934 | I26: 1.0265237
A27: 95 % интервал, верхняя граница | C27: 1 | D27: 1.0781287 | E27: 1.0872349 | F27: 1.1537422 | G27: 1.0902226 | H27: 1.1090709 | I27: 1.1473251
A28: Ст. откл. остатков завода (лог.): 0.073 — используется как идиосинкратический шум в Монте-Карло

Sheet Индекс_динамики
A1: Индекс активности «Азота» (2023 = 1) и сравнение с выпуском аммиака в России
A3: Год | B3: exp(γt) США, 2017=1 | C3: Индекс «Азота», 2023=1 | D3: Выпуск аммиака РФ, млн т | E3: Индекс РФ, 2023=1 | F3: Примечание
A4: 2017 | B4: =Панель_EPA!C25 -> 1 | C4: =B4/$B$10 -> 0.92207315 | D4: 17.1 | E4: =D4/$D$10 -> 0.99130435
A5: 2018 | B5: =Панель_EPA!D25 -> 1.0333593 | C5: =B5/$B$10 -> 0.95283282 | F5: Выпуск РФ за 2018 г. в найденных источниках не приведён
A6: 2019 | B6: =Панель_EPA!E25 -> 1.0350458 | C6: =B6/$B$10 -> 0.95438793 | D6: 19.2 | E6: =D6/$D$10 -> 1.1130435 | F6: ≈19,2 млн т: расчёт по росту 2020 г. на 2,1 % (RUPEC)
A7: 2020 | B7: =Панель_EPA!F25 -> 1.1005603 | C7: =B7/$B$10 -> 1.0147971 | D7: 19.6 | E7: =D7/$D$10 -> 1.1362319
A8: 2021 | B8: =Панель_EPA!G25 -> 1.0337595 | C8: =B8/$B$10 -> 0.95320191 | D8: 19.9 | E8: =D8/$D$10 -> 1.1536232
A9: 2022 | B9: =Панель_EPA!H25 -> 1.0520477 | C9: =B9/$B$10 -> 0.97006495 | D9: 17 | E9: =D9/$D$10 -> 0.98550725 | F9: Падение связано с ограничением экспорта (BusinesStat); интегрированный «Азот» затронут меньше
A10: 2023 | B10: =Панель_EPA!I25 -> 1.0845127 | C10: =B10/$B$10 -> 1 | D10: 17.25 | E10: =D10/$D$10 -> 1
A11: 2024 | C11: 1 | D11: 18.1 | E11: =D11/$D$10 -> 1.0492754 | F11: Аналоговых данных EPA за 2024 г. нет; индекс «Азота» принят 1,0
A12: 2025 | C12: 1 | D12: 18.6 | E12: =D12/$D$10 -> 1.0782609 | F12: Индекс 1,0 до учёта простоя (лист «Параметры», D2025)
A13: 2026 | C13: 1 | F13: Оценка на полный год; индекс 1,0 до учёта простоя
A15: Источники ряда РФ: 2017, 2021 — BusinesStat (marketing.rbc.ru, 2022); 2020 — RUPEC, 01.02.2021; 2022 — 17,0 млн т (BusinesStat, 2023); 2023 — ≈17,25 млн т (2024 г. +4,9 %, TAdviser); 2024 — 18,1 и 2025 — 18,6 млн т (Росстат по PortNews, 09.02.2026).
A16: Ряд РФ не используется в расчёте: национальный выпуск отражает экспортный шок 2022 г., а «Азот» перерабатывает аммиак на месте. Он служит проверкой знака изменений.

Sheet Ряды_Азот
A1: Модельные ряды выбросов АО «Невинномысский Азот», 2017–2026 гг., тыс. т
A2: Не отчётные данные предприятия, а оценка по заводам-аналогам. Все ячейки — формулы от листа «Параметры». Интервалы 5–95 % — Монте-Карло, 20 000 испытаний (значения).
A4: Год | B4: Индекс активности | C4: Доля года в работе | D4: CO2 полный, граница EPA | E4: CO2 в карбамид | F4: CO2 в атмосферу, граница МГЭИК | G4: N2O, CO2-экв. (без очистки) | H4: N2O, CO2-экв. (очистка уровня США) | I4: Всего CO2-экв., МГЭИК, без очистки N2O | J4: Процессный CO2 аммиака (технологический) | K4: Пищевая CO2 | L4: Свободный технологический CO2 | M4: CO2 полный: 5 % | N4: CO2 полный: 95 % | O4: N2O без очистки: 5 % | P4: N2O без очистки: 95 % | Q4: Процессный CO2: 5 % | R4: Процессный CO2: 95 %
A5: 2017 | B5: =Индекс_динамики!C4 -> 0.92207315 | C5: 1 | D5: =Параметры!$D$5*Параметры!$D$6*B5*C5 -> 2010.2096 | E5: =Параметры!$D$13*Параметры!$D$14*B5*C5 -> 337.93981 | F5: =D5-E5 -> 1672.2698 | G5: =Параметры!$D$8*Параметры!$D$9*Параметры!$D$10/1000*Параметры!$D$12*B5*C5 -> 2207.1527 | H5: =Параметры!$D$5*Параметры!$D$7*Параметры!$D$11*B5*C5 -> 448.96335 | I5: =F5+G5 -> 3879.4224 | J5: =Параметры!$D$5*Параметры!$D$7*B5*C5 -> 1203.6984 | K5: 0 | L5: =J5-E5-K5 -> 865.75859 | M5: 1743 | N5: 2461 | O5: 1846 | P5: 2618 | Q5: 1026 | R5: 1494
A6: 2018 | B6: =Индекс_динамики!C5 -> 0.95283282 | C6: 1 | D6: =Параметры!$D$5*Параметры!$D$6*B6*C6 -> 2077.2687 | E6: =Параметры!$D$13*Параметры!$D$14*B6*C6 -> 349.21323 | F6: =D6-E6 -> 1728.0554 | G6: =Параметры!$D$8*Параметры!$D$9*Параметры!$D$10/1000*Параметры!$D$12*B6*C6 -> 2280.7816 | H6: =Параметры!$D$5*Параметры!$D$7*Параметры!$D$11*B6*C6 -> 463.94044 | I6: =F6+G6 -> 4008.837 | J6: =Параметры!$D$5*Параметры!$D$7*B6*C6 -> 1243.8529 | K6: =Параметры!$D$15/12 -> 2.6666667 | L6: =J6-E6-K6 -> 891.97298 | M6: 1803 | N6: 2539 | O6: 1908 | P6: 2703 | Q6: 1063 | R6: 1547
A7: 2019 | B7: =Индекс_динамики!C6 -> 0.95438793 | C7: 1 | D7: =Параметры!$D$5*Параметры!$D$6*B7*C7 -> 2080.6589 | E7: =Параметры!$D$13*Параметры!$D$14*B7*C7 -> 349.78318 | F7: =D7-E7 -> 1730.8758 | G7: =Параметры!$D$8*Параметры!$D$9*Параметры!$D$10/1000*Параметры!$D$12*B7*C7 -> 2284.5041 | H7: =Параметры!$D$5*Параметры!$D$7*Параметры!$D$11*B7*C7 -> 464.69763 | I7: =F7+G7 -> 4015.3798 | J7: =Параметры!$D$5*Параметры!$D$7*B7*C7 -> 1245.883 | K7: =Параметры!$D$15*C7 -> 32 | L7: =J7-E7-K7 -> 864.09978 | M7: 1801 | N7: 2545 | O7: 1908 | P7: 2712 | Q7: 1061 | R7: 1547
A8: 2020 | B8: =Индекс_динамики!C7 -> 1.0147971 | C8: 1 | D8: =Параметры!$D$5*Параметры!$D$6*B8*C8 -> 2212.3568 | E8: =Параметры!$D$13*Параметры!$D$14*B8*C8 -> 371.92313 | F8: =D8-E8 -> 1840.4337 | G8: =Параметры!$D$8*Параметры!$D$9*Параметры!$D$10/1000*Параметры!$D$12*B8*C8 -> 2429.1046 | H8: =Параметры!$D$5*Параметры!$D$7*Параметры!$D$11*B8*C8 -> 494.11124 | I8: =F8+G8 -> 4269.5383 | J8: =Параметры!$D$5*Параметры!$D$7*B8*C8 -> 1324.7427 | K8: =Параметры!$D$15*C8 -> 32 | L8: =J8-E8-K8 -> 920.81952 | M8: 1923 | N8: 2701 | O8: 2031 | P8: 2869 | Q8: 1132 | R8: 1640
A9: 2021 | B9: =Индекс_динамики!C8 -> 0.95320191 | C9: 1 | D9: =Параметры!$D$5*Параметры!$D$6*B9*C9 -> 2078.0733 | E9: =Параметры!$D$13*Параметры!$D$14*B9*C9 -> 349.3485 | F9: =D9-E9 -> 1728.7248 | G9: =Параметры!$D$8*Параметры!$D$9*Параметры!$D$10/1000*Параметры!$D$12*B9*C9 -> 2281.6651 | H9: =Параметры!$D$5*Параметры!$D$7*Параметры!$D$11*B9*C9 -> 464.12015 | I9: =F9+G9 -> 4010.3899 | J9: =Параметры!$D$5*Параметры!$D$7*B9*C9 -> 1244.3347 | K9: =Параметры!$D$15*C9 -> 32 | L9: =J9-E9-K9 -> 862.9862 | M9: 1800 | N9: 2541 | O9: 1906 | P9: 2706 | Q9: 1060 | R9: 1544
A10: 2022 | B10: =Индекс_динамики!C9 -> 0.97006495 | C10: 1 | D10: =Параметры!$D$5*Параметры!$D$6*B10*C10 -> 2114.8364 | E10: =Параметры!$D$13*Параметры!$D$14*B10*C10 -> 355.5288 | F10: =D10-E10 -> 1759.3076 | G10: =Параметры!$D$8*Параметры!$D$9*Параметры!$D$10/1000*Параметры!$D$12*B10*C10 -> 2322.0299 | H10: =Параметры!$D$5*Параметры!$D$7*Параметры!$D$11*B10*C10 -> 472.33087 | I10: =F10+G10 -> 4081.3375 | J10: =Параметры!$D$5*Параметры!$D$7*B10*C10 -> 1266.3482 | K10: =Параметры!$D$15*C10 -> 32 | L10: =J10-E10-K10 -> 878.81935 | M10: 1830 | N10: 2600 | O10: 1935 | P10: 2765 | Q10: 1079 | R10: 1579
A11: 2023 | B11: =Индекс_динамики!C10 -> 1 | C11: 1 | D11: =Параметры!$D$5*Параметры!$D$6*B11*C11 -> 2180.0977 | E11: =Параметры!$D$13*Параметры!$D$14*B11*C11 -> 366.5 | F11: =D11-E11 -> 1813.5977 | G11: =Параметры!$D$8*Параметры!$D$9*Параметры!$D$10/1000*Параметры!$D$12*B11*C11 -> 2393.685 | H11: =Параметры!$D$5*Параметры!$D$7*Параметры!$D$11*B11*C11 -> 486.90644 | I11: =F11+G11 -> 4207.2827 | J11: =Параметры!$D$5*Параметры!$D$7*B11*C11 -> 1305.4261 | K11: =Параметры!$D$15*C11 -> 32 | L11: =J11-E11-K11 -> 906.92615 | M11: 1899 | N11: 2652 | O11: 2009 | P11: 2819 | Q11: 1122 | R11: 1618
A12: 2024 | B12: =Индекс_динамики!C11 -> 1 | C12: 1 | D12: =Параметры!$D$5*Параметры!$D$6*B12*C12 -> 2180.0977 | E12: =Параметры!$D$13*Параметры!$D$14*B12*C12 -> 366.5 | F12: =D12-E12 -> 1813.5977 | G12: =Параметры!$D$8*Параметры!$D$9*Параметры!$D$10/1000*Параметры!$D$12*B12*C12 -> 2393.685 | H12: =Параметры!$D$5*Параметры!$D$7*Параметры!$D$11*B12*C12 -> 486.90644 | I12: =F12+G12 -> 4207.2827 | J12: =Параметры!$D$5*Параметры!$D$7*B12*C12 -> 1305.4261 | K12: =Параметры!$D$15*C12 -> 32 | L12: =J12-E12-K12 -> 906.92615 | M12: 1906 | N12: 2645 | O12: 2016 | P12: 2819 | Q12: 1122 | R12: 1611
A13: 2025 | B13: =Индекс_динамики!C12 -> 1 | C13: =1-Параметры!$D$16/365 -> 1 | D13: =Параметры!$D$5*Параметры!$D$6*B13*C13 -> 2180.0977 | E13: =Параметры!$D$13*Параметры!$D$14*B13*C13 -> 366.5 | F13: =D13-E13 -> 1813.5977 | G13: =Параметры!$D$8*Параметры!$D$9*Параметры!$D$10/1000*Параметры!$D$12*B13*C13 -> 2393.685 | H13: =Параметры!$D$5*Параметры!$D$7*Параметры!$D$11*B13*C13 -> 486.90644 | I13: =F13+G13 -> 4207.2827 | J13: =Параметры!$D$5*Параметры!$D$7*B13*C13 -> 1305.4261 | K13: =Параметры!$D$15*C13 -> 32 | L13: =J13-E13-K13 -> 906.92615 | M13: 1902 | N13: 2656 | O13: 2014 | P13: 2820 | Q13: 1119 | R13: 1610
A14: 2026 | B14: =Индекс_динамики!C13 -> 1 | C14: =1-Параметры!$D$17/365 -> 1 | D14: =Параметры!$D$5*Параметры!$D$6*B14*C14 -> 2180.0977 | E14: =Параметры!$D$13*Параметры!$D$14*B14*C14 -> 366.5 | F14: =D14-E14 -> 1813.5977 | G14: =Параметры!$D$8*Параметры!$D$9*Параметры!$D$10/1000*Параметры!$D$12*B14*C14 -> 2393.685 | H14: =Параметры!$D$5*Параметры!$D$7*Параметры!$D$11*B14*C14 -> 486.90644 | I14: =F14+G14 -> 4207.2827 | J14: =Параметры!$D$5*Параметры!$D$7*B14*C14 -> 1305.4261 | K14: =Параметры!$D$15*C14 -> 32 | L14: =J14-E14-K14 -> 906.92615 | M14: 1901 | N14: 2650 | O14: 2013 | P14: 2821 | Q14: 1121 | R14: 1613
A16: Пояснения. «Граница EPA»: процессный CO2 включает CO2, затем связанный в карбамид. «Граница МГЭИК»: CO2 карбамида вычитается, как в национальной отчётности. N2O «без очистки» — российская удельная эмиссия 8–9 кг/т HNO3; «очистка уровня США» — отношение N2O к CO2 у аналогов. Какой вариант верен, зависит от наличия каталитического разложения N2O на агрегатах азотной кислоты «Азота».
A17: Интервалы Монте-Карло учитывают мощность (1,0–1,35 млн т), разброс удельных выбросов аналогов, бутстреп годовых эффектов и шум отдельного завода (σ = 0,073) при нулевом простое; карбамид и простои в интервалы не входят.

Sheet Близнецы
A1: Проверка «индексом подобия»: «Азот» как масштабированная копия завода-аналога
A2: Ряд = индекс масштаба × полные выбросы CO2 завода-аналога. Показывает реалистичные годовые колебания отдельного завода, а не среднего по отрасли.
A4: Год | B4: Verdigris, CO2 полный, т | C4: Port Neal, CO2 полный, т | D4: «Азот» как 0,96 × Verdigris, тыс. т | E4: «Азот» как 0,94 × Port Neal, тыс. т | F4: Основная оценка (лист «Ряды_Азот»), тыс. т
A5: 2017 | B5: 2294003.7 | C5: 2343845.5 | D5: =Аналоги_CF!$H$7*B5/1000 -> 2199.2102 | E5: =Аналоги_CF!$H$6*C5/1000 -> 2210.4559 | F5: =Ряды_Азот!D5 -> 2010.2096
A6: 2018 | B6: 2223728.5 | C6: 2486125.8 | D6: =Аналоги_CF!$H$7*B6/1000 -> 2131.8389 | E6: =Аналоги_CF!$H$6*C6/1000 -> 2344.639 | F6: =Ряды_Азот!D6 -> 2077.2687
A7: 2019 | B7: 2075193.4 | C7: 2432398.8 | D7: =Аналоги_CF!$H$7*B7/1000 -> 1989.4416 | E7: =Аналоги_CF!$H$6*C7/1000 -> 2293.9696 | F7: =Ряды_Азот!D7 -> 2080.6589
A8: 2020 | B8: 2273412.5 | C8: 2499053.3 | D8: =Аналоги_CF!$H$7*B8/1000 -> 2179.4698 | E8: =Аналоги_CF!$H$6*C8/1000 -> 2356.8308 | F8: =Ряды_Азот!D8 -> 2212.3568
A9: 2021 | B9: 2048312.7 | C9: 2223422 | D9: =Аналоги_CF!$H$7*B9/1000 -> 1963.6717 | E9: =Аналоги_CF!$H$6*C9/1000 -> 2096.8858 | F9: =Ряды_Азот!D9 -> 2078.0733
A10: 2022 | B10: 2226326.9 | C10: 2563756 | D10: =Аналоги_CF!$H$7*B10/1000 -> 2134.3299 | E10: =Аналоги_CF!$H$6*C10/1000 -> 2417.8512 | F10: =Ряды_Азот!D10 -> 2114.8364
A11: 2023 | B11: 2106706.9 | C11: 2599267.7 | D11: =Аналоги_CF!$H$7*B11/1000 -> 2019.6529 | E11: =Аналоги_CF!$H$6*C11/1000 -> 2451.3419 | F11: =Ряды_Азот!D11 -> 2180.0977

Sheet Источники
A1: Источники
A3: 1. U.S. EPA. Greenhouse Gas Reporting Program, Envirofacts API (data.epa.gov/efservice): G_SUBPART_LEVEL_INFORMATION, V_SUBPART_LEVEL_INFORMATION, PUB_FACTS_SECTOR_GHG_EMISSION, PUB_DIM_FACILITY. Выгружено 14.10.2026.
A4: 2. U.S. EPA. Subpart G Information Sheet (Ammonia Manufacturing). URL: https://www.epa.gov/ghgreporting/subpart-g-information-sheet
A5: 3. CF Industries Holdings, Inc. Form 10-K for the fiscal year ended December 31, 2022. URL: https://www.sec.gov/Archives/edgar/data/1324404/000132440423000006/cf-20221231.htm
A6: 4. Jörß W., Ludig S., Schneider L. Mitigation potentials for emissions of nitrous oxide from chemical industry in industrialised countries world-wide. Berlin: Öko-Institut e.V., 2023.
A7: 5. IEA. Ammonia Technology Roadmap. Paris, 2021 (соотношение угольной и газовой технологии по CO2 — по изложению Ammonia Energy Association).
A8: 6. Производство аммиака в России в 2025 году выросло на 2,8 % — до 18,6 млн тонн // PortNews. 09.02.2026.
A9: 7. BusinesStat: обзоры рынка аммиака в России (marketing.rbc.ru, 2022–2024); RUPEC, 01.02.2021.
A10: 8. Остановки «Азота»: The Moscow Times, 16.06.2025 и 16.05.2026; Kyiv Post, 04.12.2025 (даты событий; сведения о мощностях в этих материалах не подтверждены независимо).
